apimatic_calculator/__init__.py
apimatic_calculator/api_helper.py
apimatic_calculator/apimatic_calculator_client.py
apimatic_calculator/configuration.py
apimatic_calculator/decorators.py
apimatic_calculator/controllers/__init__.py
apimatic_calculator/controllers/base_controller.py
apimatic_calculator/controllers/simple_calculator_controller.py
apimatic_calculator/exceptions/__init__.py
apimatic_calculator/exceptions/api_exception.py
apimatic_calculator/http/__init__.py
apimatic_calculator/http/http_call_back.py
apimatic_calculator/http/http_client.py
apimatic_calculator/http/http_context.py
apimatic_calculator/http/http_method_enum.py
apimatic_calculator/http/http_request.py
apimatic_calculator/http/http_response.py
apimatic_calculator/http/requests_client.py
apimatic_calculator/models/__init__.py
apimatic_calculator/models/operation_type_enum.py
tests/__init__.py
tests/http_response_catcher.py
tests/test_helper.py
tests/controllers/__init__.py
tests/controllers/controller_test_base.py
tests/controllers/test_simple_calculator_controller.py
apimatic_calculator-1.0.dist-info/LICENSE
apimatic_calculator-1.0.dist-info/METADATA
apimatic_calculator-1.0.dist-info/WHEEL
apimatic_calculator-1.0.dist-info/top_level.txt
apimatic_calculator-1.0.dist-info/RECORD
